_example.py
audio_commands.py
belt_cli.py
crypt_commands.py
dns_commands.py
domain_commands.py
tls_commands.py
belt_cli-0.1.8.dist-info/LICENSE
belt_cli-0.1.8.dist-info/METADATA
belt_cli-0.1.8.dist-info/WHEEL
belt_cli-0.1.8.dist-info/entry_points.txt
belt_cli-0.1.8.dist-info/RECORD
