Metadata-Version: 2.1
Name: belt-cli
Version: 0.1.8
Summary: CLI toolbelt
Home-page: https://github.com/daveio/belt
License: MIT
Author: Dave Williams
Author-email: dave@dave.io
Requires-Python: >=3.12,<4.0
Classifier: Development Status :: 4 - Beta
Classifier: License :: OSI Approved :: MIT License
Classifier: Programming Language :: Python
Classifier: Programming Language :: Python :: 3
Classifier: Programming Language :: Python :: 3.12
Classifier: Programming Language :: Python :: 3.13
Classifier: Programming Language :: Python :: Implementation :: CPython
Classifier: Programming Language :: Python :: Implementation :: PyPy
Requires-Dist: chevron (>=0.14.0,<0.15.0)
Requires-Dist: click (>=8.1.8,<9.0.0)
Requires-Dist: cryptography (>=44.0.0,<45.0.0)
Requires-Dist: dnspython (>=2.7.0,<3.0.0)
Requires-Dist: mutagen (>=1.47.0,<2.0.0)
Requires-Dist: requests (>=2.32.3,<3.0.0)
Requires-Dist: showcert (>=0.2.12,<0.3.0)
Requires-Dist: types-chevron (>=0.14.2.20240310,<0.15.0.0)
Requires-Dist: wireguard-tools (>=0.5.0,<0.6.0)
Project-URL: Repository, https://github.com/daveio/belt
